marvin_toolkit/__init__.py
marvin_toolkit/carregar_parametros.py
marvin_toolkit/qase.py
marvin_toolkit/ui.py
marvin_toolkit/utils.py
marvin_toolkit-0.3.0.dist-info/METADATA
marvin_toolkit-0.3.0.dist-info/WHEEL
marvin_toolkit-0.3.0.dist-info/top_level.txt
marvin_toolkit-0.3.0.dist-info/RECORD
