Metadata-Version: 2.4
Name: marvin_toolkit
Version: 0.3.0
Summary: Biblioteca de automação padrão para a equipe de QA (Projeto Marvin).
Requires-Python: >=3.8
Requires-Dist: requests
Requires-Dist: pandas
Requires-Dist: openpyxl
Requires-Dist: jsonc-parser
